rlma.py
rlma-0.2.0.dist-info/METADATA
rlma-0.2.0.dist-info/WHEEL
rlma-0.2.0.dist-info/top_level.txt
rlma-0.2.0.dist-info/RECORD
