Metadata-Version: 2.4
Name: rlma
Version: 0.2.0
Summary: Robust Linear Matching Algorithm (RLMA) for variable association detection
Home-page: https://github.com/francisamofa/rlma
Author: Francis Jemisiham Amofa
Author-email: jemisihamamofa@gmail.com
Classifier: Programming Language :: Python :: 3
Classifier: License :: OSI Approved :: MIT License
Classifier: Operating System :: OS Independent
Requires-Python: >=3.6
Requires-Dist: numpy
Requires-Dist: pandas
Requires-Dist: scipy
Requires-Dist: scikit-learn
Dynamic: author
Dynamic: author-email
Dynamic: classifier
Dynamic: description
Dynamic: description-content-type
Dynamic: home-page
Dynamic: requires-dist
Dynamic: requires-python
Dynamic: summary
